AUTHORS
COPYING
MANIFEST.in
README.md
setup.py
PyAjam.egg-info/PKG-INFO
PyAjam.egg-info/SOURCES.txt
PyAjam.egg-info/dependency_links.txt
PyAjam.egg-info/top_level.txt
pyajam/__init__.py
pyajam/pyajam.py